thanhtungcalendartspt/Leaps.py
thanhtungcalendartspt/ListSearch.py
thanhtungcalendartspt/NewMoonGMT0.py
thanhtungcalendartspt/SolsticeGMT7.py
thanhtungcalendartspt/TsptCalendar.py
thanhtungcalendartspt/__init__.py
calendarthanhtungtspt-1.0.0.dist-info/LICENSE
calendarthanhtungtspt-1.0.0.dist-info/METADATA
calendarthanhtungtspt-1.0.0.dist-info/WHEEL
calendarthanhtungtspt-1.0.0.dist-info/top_level.txt
calendarthanhtungtspt-1.0.0.dist-info/RECORD
